{
  "id": "skd.variants.028",
  "title": "СКД в 1С: одна схема компоновки может давать несколько вариантов отчета",
  "source": "Хрусталева. Разработка сложных отчетов в 1С:Предприятии. Система компоновки данных",
  "topic": "skd",
  "tags": [
    "skd",
    "variants",
    "settings",
    "report"
  ],
  "text": "Одна схема компоновки данных в 1С может использоваться для построения нескольких вариантов отчета. Конечный вид результата определяется не только схемой, но и примененными настройками компоновки. Это позволяет на одной базе данных и на одной логике получения данных строить разные представления: таблицы, группировки, диаграммы и вложенные отчеты без дублирования прикладного кода.",
  "priority": 0.99
}
