{
  "id": "skd.resources_required_for_table.063",
  "title": "Для таблиц и диаграмм СКД ресурсы обязательны",
  "source": "Хрусталева. Разработка сложных отчетов в 1С. СКД",
  "topic": "skd_core",
  "tags": [
    "skd",
    "resources",
    "tables",
    "charts"
  ],
  "text": "В СКД ресурсы — это итоговые данные, которые рассчитываются системой на основе детальных записей. Для вывода таблиц и диаграмм ресурсы обязательны, потому что именно они формируют значения на пересечении строк и колонок или на осях диаграммы. Для простого списка ресурсы могут не понадобиться, но для аналитического отчета они проектируются сразу.",
  "priority": 0.99
}
